easy_logging/__init__.py
easy_logging/easylogging.py
easy_logging/main.py
easy_logging_setup-0.0.2.dist-info/LICENSE
easy_logging_setup-0.0.2.dist-info/METADATA
easy_logging_setup-0.0.2.dist-info/WHEEL
easy_logging_setup-0.0.2.dist-info/top_level.txt
easy_logging_setup-0.0.2.dist-info/RECORD
