Metadata-Version: 2.1
Name: easy-logging-setup
Version: 0.0.2
Summary: A Easy Logging Tool for Python
Author-email: Kien Nguyen <kiennguyenvnmos@gmail.com>
License: Copyright (c) 2018 The Python Packaging Authority
Project-URL: Homepage, https://github.com/Kiennguyen08/easy-logging-setup
Project-URL: Issues, https://github.com/Kiennguyen08/easy-logging-setup/issues
Classifier: Programming Language :: Python :: 3
Classifier: License :: OSI Approved :: MIT License
Classifier: Operating System :: OS Independent
Requires-Python: >=3.8
License-File: LICENSE
Requires-Dist: python-json-logger ==2.0.7
Requires-Dist: pyyaml ==6.0.1
